vcf_creator/__init__.py
vcf_creator/__main__.py
vcf_creator/cli.py
vcf_creator/vcf.py
vcf_creator/tests/__init__.py
vcf_creator/tests/test_vcf.py
vcf_creator-1.1.1.dist-info/LICENSE
vcf_creator-1.1.1.dist-info/METADATA
vcf_creator-1.1.1.dist-info/WHEEL
vcf_creator-1.1.1.dist-info/entry_points.txt
vcf_creator-1.1.1.dist-info/top_level.txt
vcf_creator-1.1.1.dist-info/RECORD
