Metadata-Version: 2.1
Name: vcf-creator
Version: 1.1.1
Summary: Generate vCard file from CSV
Home-page: https://github.com/animesh-chouhan/vcf-creator
Author: Animesh Singh Chouhan
Author-email: animeshsingh.iitkgp@gmail.com
License: UNKNOWN
Project-URL: Bug Tracker, https://github.com/animesh-chouhan/vcf-creator/issues
Platform: UNKNOWN
Classifier: Programming Language :: Python :: 3
Classifier: License :: OSI Approved :: MIT License
Classifier: Operating System :: OS Independent
Requires-Python: >=3.6
License-File: LICENSE
